<?xml version="1.0" encoding="US-ASCII" standalone="yes"?>
<GobyMonitor>
  <Document>
    <Fields>
      <Field>
        <Name>Customer No</Name>
        <Data>2264</Data>
      </Field>
      <Field>
        <Name>Customer Name</Name>
        <Data>SERVICE DEPT</Data>
      </Field>
      <Field>
        <Name>Order No</Name>
        <Data>400019</Data>
      </Field>
      <Field>
        <Name>PO No</Name>
        <Data>777</Data>
      </Field>
      <Field>
        <Name>Document Type</Name>
        <Data>Sales Confirmation</Data>
      </Field>
      <Field>
        <Name>PO Number</Name>
        <Data>777</Data>
      </Field>
      <Field>
        <Name>CreditStatus</Name>
        <Data>Order Credit Limit</Data>
      </Field>
      <Field>
        <Name>Order Date</Name>
        <Data>04/09/14</Data>
      </Field>
      <Field>
        <Name>wsf_inbox</Name>
        <Data>generalinbox</Data>
      </Field>
    </Fields>
    <Files>
      <File>
        <Filespec>400019.PDF</Filespec>
      </File>
    </Files>
  </Document>
</GobyMonitor>